gitignoreio/__init__.py
gitignoreio/_version.py
gitignoreio/cli/__init__.py
gitignoreio/cli/updategitignore.py
gitignoreio-0.1.5.dist-info/METADATA
gitignoreio-0.1.5.dist-info/RECORD
gitignoreio-0.1.5.dist-info/WHEEL
gitignoreio-0.1.5.dist-info/entry_points.txt
gitignoreio-0.1.5.dist-info/top_level.txt
