Metadata-Version: 2.1
Name: gitignoreio
Version: 0.1.5
Summary: Update .gitignore from config and gitignore.io.
Home-page: https://github.com/altendky/gitignoreio
Author: Kyle Altendorf
Author-email: sda@fstab.net
License: UNKNOWN
Platform: UNKNOWN
Classifier: Development Status :: 4 - Beta
Classifier: Intended Audience :: Developers
Classifier: Programming Language :: Python :: 2
Classifier: Programming Language :: Python :: 2.7
Classifier: Programming Language :: Python :: 3
Classifier: Programming Language :: Python :: 3.4
Classifier: Programming Language :: Python :: 3.5
Classifier: Programming Language :: Python :: 3.6
Requires-Dist: click
Requires-Dist: requests
